gamerl/dqn/jax/__init__.py
gamerl/dqn/jax/dqn.py
gamerl/dqn/jax/dqn_examples.py
gamerl/dqn/jax/replay_buffers.py
gamerl.dqn.jax-0.1.1.dist-info/LICENSE
gamerl.dqn.jax-0.1.1.dist-info/METADATA
gamerl.dqn.jax-0.1.1.dist-info/WHEEL
gamerl.dqn.jax-0.1.1.dist-info/top_level.txt
gamerl.dqn.jax-0.1.1.dist-info/RECORD
